xyz_person/__init__.py
xyz_person/admin.py
xyz_person/apis.py
xyz_person/apps.py
xyz_person/auth_backens.py
xyz_person/choices.py
xyz_person/helper.py
xyz_person/importers.py
xyz_person/models.py
xyz_person/receivers.py
xyz_person/serializers.py
xyz_person/validators.py
xyz_person/migrations/0001_initial.py
xyz_person/migrations/__init__.py
xyz_person-0.2.0.dist-info/METADATA
xyz_person-0.2.0.dist-info/WHEEL
xyz_person-0.2.0.dist-info/top_level.txt
xyz_person-0.2.0.dist-info/RECORD
